AUTHORS.rst
CONTRIBUTING.rst
HISTORY.rst
LICENSE
MANIFEST.in
README.rst
VERSION
setup.cfg
setup.py
docs/Makefile
docs/authors.rst
docs/conf.py
docs/contributing.rst
docs/history.rst
docs/index.rst
docs/installation.rst
docs/make.bat
docs/modules.rst
docs/readme.rst
docs/simple_dependency_resolver.rst
docs/usage.rst
requirements/ci.txt
requirements/prod.txt
requirements/test.txt
simple_dependency_resolver/__init__.py
simple_dependency_resolver/simple_dependency_resolver.py
simple_dependency_resolver.egg-info/PKG-INFO
simple_dependency_resolver.egg-info/SOURCES.txt
simple_dependency_resolver.egg-info/dependency_links.txt
simple_dependency_resolver.egg-info/not-zip-safe
simple_dependency_resolver.egg-info/requires.txt
simple_dependency_resolver.egg-info/top_level.txt
tests/__init__.py
tests/test_simple_dependency_resolver.py