Metadata-Version: 2.1
Name: simple-dependency-resolver
Version: 0.1.2
Summary: Simple text based dependency resolution algorithm
Home-page: https://gitlab.com/paul_armstrong/simple_dependency_resolver
Author: Paul Armstrong
Author-email: parmstrong@gitlab.com
License: MIT license
Keywords: simple_dependency_resolver
Platform: UNKNOWN
Classifier: Development Status :: 2 - Pre-Alpha
Classifier: Intended Audience :: Developers
Classifier: License :: OSI Approved :: MIT License
Classifier: Natural Language :: English
Classifier: Programming Language :: Python :: 3
Classifier: Programming Language :: Python :: 3.6
Classifier: Programming Language :: Python :: 3.7
Classifier: Programming Language :: Python :: 3.8
Requires-Python: >=3.6
Provides-Extra: ci-checks
License-File: LICENSE
License-File: AUTHORS.rst
